[
  {
    "no": 1,
    "title": "qwer",
    "content": "qwer",
    "writer": "q",
    "password": "q",
    "viewCount": 1,
    "createdDate": 1688108547884
  },
  {
    "no": 3,
    "title": "q",
    "content": "q",
    "writer": "q",
    "password": "q",
    "viewCount": 0,
    "createdDate": 1688370492090
  },
  {
    "no": 4,
    "title": "w",
    "content": "w",
    "writer": "w",
    "password": "w",
    "viewCount": 0,
    "createdDate": 1688370495731
  },
  {
    "no": 7,
    "title": "e",
    "content": "e",
    "writer": "e",
    "password": "e",
    "viewCount": 0,
    "createdDate": 1688372727931
  },
  {
    "no": 8,
    "title": "r",
    "content": "r",
    "writer": "r",
    "password": "r",
    "viewCount": 0,
    "createdDate": 1688373419124
  },
  {
    "no": 11,
    "title": "z",
    "content": "z",
    "writer": "z",
    "password": "z",
    "viewCount": 0,
    "createdDate": 1688373469885
  },
  {
    "no": 12,
    "title": "zzz",
    "content": "zzzzzzz",
    "writer": "z",
    "password": "z",
    "viewCount": 0,
    "createdDate": 1688622409277
  },
  {
    "no": 13,
    "title": "do",
    "content": "dodododo",
    "writer": "dodo",
    "password": "do",
    "viewCount": 0,
    "createdDate": 1688622422772
  },
  {
    "no": 14,
    "title": "test",
    "content": "tests",
    "writer": "a",
    "password": "a",
    "viewCount": 0,
    "createdDate": 1688954272540
  },
  {
    "no": 15,
    "title": "test",
    "content": "test",
    "writer": "test",
    "password": "test",
    "viewCount": 0,
    "createdDate": 1688955005425
  },
  {
    "no": 16,
    "title": "test",
    "content": "test",
    "writer": "test",
    "password": "tes",
    "viewCount": 0,
    "createdDate": 1688955199592
  },
  {
    "no": 17,
    "title": "test",
    "content": "test",
    "writer": "tes",
    "password": "tes",
    "viewCount": 0,
    "createdDate": 1688955318482
  },
  {
    "no": 18,
    "title": "test",
    "content": "tes",
    "writer": "tes",
    "password": "tes",
    "viewCount": 0,
    "createdDate": 1688956159148
  },
  {
    "no": 19,
    "title": "test",
    "content": "test",
    "writer": "test",
    "password": "test",
    "viewCount": 0,
    "createdDate": 1688956245151
  },
  {
    "no": 20,
    "title": "test",
    "content": "test",
    "writer": "test",
    "password": "test",
    "viewCount": 0,
    "createdDate": 1688957185636
  },
  {
    "no": 21,
    "title": "test",
    "content": "test",
    "writer": "test",
    "password": "test",
    "viewCount": 0,
    "createdDate": 1688957270991
  }
]